{
"file":"abagxh0.png",
"frames":{
"abagxh_a1_cn_png":{"x":190,"y":99,"w":113,"h":99,"offX":31,"offY":40,"sourceW":187,"sourceH":194},
"btn_abagxh_a3_cn_png":{"x":190,"y":3,"w":189,"h":53,"offX":7,"offY":12,"sourceW":204,"sourceH":76},
"btn_abagxh_a4_cn_png":{"x":307,"y":60,"w":68,"h":89,"offX":11,"offY":0,"sourceW":89,"sourceH":96},
"btn_abagxh_a5_cn_png":{"x":130,"y":3,"w":56,"h":199,"offX":17,"offY":5,"sourceW":89,"sourceH":212},
"btn_abagxh_a6_cn_png":{"x":383,"y":3,"w":57,"h":92,"offX":16,"offY":3,"sourceW":89,"sourceH":96},
"btn_abagxh_a7_cn_png":{"x":70,"y":3,"w":56,"h":210,"offX":19,"offY":0,"sourceW":89,"sourceH":212},
"btn_abagxh_a8_cn_png":{"x":379,"y":99,"w":66,"h":95,"offX":14,"offY":1,"sourceW":89,"sourceH":96},
"btn_abagxh_a9_cn_png":{"x":3,"y":3,"w":63,"h":211,"offX":13,"offY":1,"sourceW":89,"sourceH":212}}}