{
"file":"bfai1.png",
"frames":{
"bfai_c1_cn_png":{"x":409,"y":434,"w":402,"h":103,"offX":130,"offY":25,"sourceW":640,"sourceH":150},
"bfai_c2_cn_png":{"x":3,"y":542,"w":523,"h":149,"offX":117,"offY":0,"sourceW":640,"sourceH":150},
"bfai_c9_cn_png":{"x":3,"y":96,"w":627,"h":203,"offX":4,"offY":17,"sourceW":640,"sourceH":240},
"bfai_c15_png":{"x":781,"y":3,"w":105,"h":94,"offX":25,"offY":26,"sourceW":150,"sourceH":150},
"bfai_c16_cn_png":{"x":3,"y":434,"w":402,"h":103,"offX":126,"offY":19,"sourceW":640,"sourceH":150},
"bfai_d2_png":{"x":3,"y":303,"w":94,"h":120,"offX":0,"offY":0,"sourceW":94,"sourceH":121},
"bfai_d3_png":{"x":101,"y":303,"w":94,"h":120,"offX":0,"offY":0,"sourceW":94,"sourceH":121},
"bfai_e2_png":{"x":781,"y":101,"w":102,"h":129},
"bfai_e3_png":{"x":634,"y":149,"w":102,"h":129},
"bfai_f3_png":{"x":3,"y":3,"w":628,"h":89,"offX":2,"offY":2,"sourceW":630,"sourceH":91},
"bfai_g7_png":{"x":3,"y":695,"w":445,"h":35},
"bfai_g8_png":{"x":635,"y":3,"w":142,"h":142,"offX":9,"offY":9,"sourceW":160,"sourceH":160},
"bfai_panel4_png":{"x":840,"y":234,"w":87,"h":304,"offX":0,"offY":0,"sourceW":87,"sourceH":310},
"bfai_panel5_png":{"x":840,"y":234,"w":87,"h":304,"offX":0,"offY":0,"sourceW":87,"sourceH":310},
"btn_bfai_a3_cn_png":{"x":385,"y":303,"w":93,"h":99,"offX":16,"offY":12,"sourceW":125,"sourceH":120},
"btn_bfai_a9_png":{"x":726,"y":542,"w":94,"h":94,"offX":10,"offY":10,"sourceW":115,"sourceH":115},
"btn_bfai_a10_png":{"x":530,"y":542,"w":94,"h":94,"offX":10,"offY":10,"sourceW":115,"sourceH":115},
"btn_bfai_a11_png":{"x":628,"y":542,"w":94,"h":94,"offX":10,"offY":10,"sourceW":115,"sourceH":115},
"btn_bfai_a12_png":{"x":726,"y":542,"w":94,"h":94,"offX":10,"offY":10,"sourceW":115,"sourceH":115},
"btn_bfai_a13_png":{"x":530,"y":542,"w":94,"h":94,"offX":10,"offY":10,"sourceW":115,"sourceH":115},
"btn_bfai_a14_png":{"x":628,"y":542,"w":94,"h":94,"offX":10,"offY":10,"sourceW":115,"sourceH":115},
"btn_bfai_a20_png":{"x":199,"y":303,"w":89,"h":120,"offX":1,"offY":0,"sourceW":90,"sourceH":120},
"btn_bfai_a21_png":{"x":292,"y":303,"w":89,"h":120,"offX":1,"offY":0,"sourceW":90,"sourceH":120},
"btn_bfai_b1_cn_png":{"x":740,"y":234,"w":96,"h":96,"offX":9,"offY":6,"sourceW":110,"sourceH":110},
"btn_bfai_b2_cn_png":{"x":634,"y":282,"w":96,"h":96,"offX":9,"offY":6,"sourceW":110,"sourceH":110},
"btn_bfai_b3_cn_png":{"x":530,"y":640,"w":84,"h":84,"offX":8,"offY":8,"sourceW":100,"sourceH":100},
"btn_bfai_b4_cn_png":{"x":618,"y":640,"w":84,"h":84,"offX":8,"offY":8,"sourceW":100,"sourceH":100},
"btn_bfai_b5_cn_png":{"x":734,"y":334,"w":96,"h":96,"offX":7,"offY":7,"sourceW":110,"sourceH":110},
"btn_bfai_b6_cn_png":{"x":482,"y":303,"w":96,"h":96,"offX":7,"offY":7,"sourceW":110,"sourceH":110},
"btn_bfai_b7_cn_png":{"x":706,"y":640,"w":84,"h":84,"offX":8,"offY":8,"sourceW":100,"sourceH":100},
"btn_bfai_b8_cn_png":{"x":794,"y":640,"w":84,"h":84,"offX":8,"offY":8,"sourceW":100,"sourceH":100}}}