{
"file":"welfare2.png",
"frames":{
"we_av_j3_cn_png":{"x":246,"y":870,"w":110,"h":110},
"we_av_j6_cn_png":{"x":360,"y":885,"w":110,"h":110},
"we_b4_png":{"x":414,"y":620,"w":232,"h":57},
"we_b5_png":{"x":703,"y":581,"w":173,"h":61},
"we_b7_png":{"x":895,"y":333,"w":70,"h":35},
"we_b8_png":{"x":880,"y":581,"w":70,"h":35},
"we_b9_png":{"x":849,"y":935,"w":68,"h":35},
"we_b10_png":{"x":589,"y":681,"w":68,"h":35},
"we_b11_png":{"x":3,"y":953,"w":71,"h":35},
"we_b12_png":{"x":702,"y":918,"w":71,"h":35},
"we_b14_png":{"x":414,"y":681,"w":171,"h":61,"offX":0,"offY":0,"sourceW":175,"sourceH":61},
"we_b19_png":{"x":3,"y":726,"w":160,"h":223},
"we_b21_png":{"x":167,"y":725,"w":75,"h":213},
"we_b23_png":{"x":895,"y":255,"w":70,"h":35},
"we_b24_png":{"x":78,"y":953,"w":70,"h":35},
"we_b27_png":{"x":895,"y":152,"w":83,"h":99},
"we_b28_png":{"x":361,"y":3,"w":176,"h":381,"offX":0,"offY":28,"sourceW":176,"sourceH":409},
"we_b42_png":{"x":702,"y":957,"w":70,"h":35},
"we_b43_png":{"x":895,"y":294,"w":70,"h":35},
"we_b44_png":{"x":826,"y":152,"w":58,"h":30},
"we_b45_png":{"x":167,"y":942,"w":58,"h":30},
"we_b50_png":{"x":777,"y":918,"w":68,"h":35},
"we_b51_png":{"x":85,"y":404,"w":79,"h":317},
"we_b52_png":{"x":3,"y":404,"w":78,"h":318},
"we_b54_png":{"x":250,"y":396,"w":78,"h":316},
"we_b55_png":{"x":332,"y":396,"w":78,"h":315},
"we_b56_png":{"x":168,"y":404,"w":78,"h":317},
"we_b71_png":{"x":776,"y":957,"w":68,"h":35},
"we_b73_cn_png":{"x":849,"y":898,"w":72,"h":33},
"we_c5_png":{"x":392,"y":746,"w":135,"h":135},
"we_c6_png":{"x":531,"y":746,"w":135,"h":135},
"we_c10_png":{"x":180,"y":3,"w":177,"h":389},
"we_d13_png":{"x":670,"y":646,"w":135,"h":135},
"we_d25_png":{"x":3,"y":3,"w":173,"h":397},
"we_f2_png":{"x":826,"y":3,"w":145,"h":145},
"we_f3_png":{"x":702,"y":785,"w":129,"h":129},
"we_f4_png":{"x":809,"y":646,"w":134,"h":134},
"we_f5_png":{"x":246,"y":725,"w":142,"h":141},
"we_k2_cn_png":{"x":474,"y":885,"w":110,"h":110},
"we_k3_cn_png":{"x":588,"y":885,"w":110,"h":110},
"we_l5_cn_png":{"x":835,"y":784,"w":110,"h":110},
"we_m3_cn_png":{"x":541,"y":197,"w":173,"h":188},
"we_m4_cn_png":{"x":718,"y":197,"w":173,"h":188},
"we_m5_cn_png":{"x":414,"y":389,"w":173,"h":188},
"we_m6_cn_png":{"x":541,"y":3,"w":281,"h":190,"offX":0,"offY":0,"sourceW":281,"sourceH":192},
"we_m7_cn_png":{"x":591,"y":389,"w":173,"h":188},
"we_m8_cn_png":{"x":768,"y":389,"w":173,"h":188},
"we_panle21_png":{"x":414,"y":581,"w":285,"h":35}}}