{
"file":"maincitya3.png",
"frames":{
"bc_f8_png":{"x":410,"y":443,"w":46,"h":40},
"bc_f14_png":{"x":360,"y":443,"w":46,"h":40},
"btn_bc_c4_cn_png":{"x":696,"y":437,"w":54,"h":55},
"btn_bc_c5_cn_png":{"x":754,"y":437,"w":54,"h":55},
"btn_bc_c6_cn_png":{"x":812,"y":437,"w":54,"h":55},
"btn_bc_c9_cn_png":{"x":870,"y":437,"w":54,"h":55},
"btn_bc_c13_cn_png":{"x":870,"y":3,"w":54,"h":55},
"btn_bc_c14_cn_png":{"x":870,"y":62,"w":54,"h":55},
"btn_bc_c15_cn_png":{"x":870,"y":121,"w":54,"h":55},
"btn_bc_c16_cn_png":{"x":861,"y":180,"w":54,"h":55},
"btn_bc_c17_cn_png":{"x":861,"y":239,"w":54,"h":55},
"btn_bc_c18_cn_png":{"x":861,"y":298,"w":54,"h":55},
"btn_bc_d7_cn_png":{"x":696,"y":335,"w":72,"h":76,"offX":1,"offY":0,"sourceW":74,"sourceH":76},
"btn_bc_d14_cn_png":{"x":775,"y":323,"w":72,"h":76,"offX":1,"offY":0,"sourceW":74,"sourceH":76},
"btn_bc_d20_cn_png":{"x":268,"y":91,"w":83,"h":84,"offX":1,"offY":0,"sourceW":85,"sourceH":84},
"btn_bc_d22_cn_png":{"x":441,"y":267,"w":81,"h":84,"offX":2,"offY":0,"sourceW":85,"sourceH":84},
"btn_bc_d26_cn_png":{"x":526,"y":355,"w":81,"h":84,"offX":3,"offY":0,"sourceW":85,"sourceH":84},
"btn_bc_d29_cn_png":{"x":3,"y":3,"w":85,"h":84},
"btn_bc_d73_cn_png":{"x":92,"y":179,"w":85,"h":84},
"btn_bc_d77_cn_png":{"x":851,"y":357,"w":72,"h":76,"offX":1,"offY":0,"sourceW":74,"sourceH":76},
"btn_bc_d107_cn_png":{"x":698,"y":3,"w":82,"h":82,"offX":1,"offY":2,"sourceW":85,"sourceH":84},
"btn_bc_d108_cn_png":{"x":784,"y":3,"w":82,"h":82,"offX":1,"offY":2,"sourceW":85,"sourceH":84},
"btn_bc_d109_cn_png":{"x":698,"y":89,"w":82,"h":82,"offX":1,"offY":2,"sourceW":85,"sourceH":84},
"btn_bc_d119_cn_png":{"x":784,"y":89,"w":82,"h":82,"offX":1,"offY":2,"sourceW":85,"sourceH":84},
"btn_bc_d152_cn_png":{"x":697,"y":175,"w":82,"h":82},
"btn_bc_d167_cn_png":{"x":180,"y":355,"w":83,"h":84},
"btn_bc_d169_cn_png":{"x":267,"y":355,"w":83,"h":84},
"btn_bc_d170_cn_png":{"x":92,"y":267,"w":84,"h":84,"offX":0,"offY":0,"sourceW":85,"sourceH":84},
"btn_bc_d172_cn_png":{"x":181,"y":3,"w":83,"h":84},
"btn_bc_d174_cn_png":{"x":92,"y":355,"w":84,"h":84,"offX":0,"offY":0,"sourceW":85,"sourceH":84},
"btn_bc_d177_cn_png":{"x":180,"y":267,"w":84,"h":84,"offX":0,"offY":0,"sourceW":85,"sourceH":84},
"btn_bc_d192_cn_png":{"x":355,"y":91,"w":82,"h":84,"offX":2,"offY":0,"sourceW":85,"sourceH":84},
"btn_bc_d195_cn_png":{"x":181,"y":91,"w":83,"h":84,"offX":1,"offY":0,"sourceW":85,"sourceH":84},
"btn_bc_d196_cn_png":{"x":355,"y":179,"w":82,"h":84,"offX":2,"offY":0,"sourceW":85,"sourceH":84},
"btn_bc_d198_cn_png":{"x":181,"y":179,"w":83,"h":84,"offX":1,"offY":0,"sourceW":85,"sourceH":84},
"btn_bc_d205_cn_png":{"x":268,"y":3,"w":83,"h":84,"offX":0,"offY":0,"sourceW":85,"sourceH":84},
"btn_bc_d206_cn_png":{"x":355,"y":267,"w":82,"h":84,"offX":2,"offY":0,"sourceW":85,"sourceH":84},
"btn_bc_d227_cn_png":{"x":268,"y":179,"w":83,"h":84,"offX":1,"offY":0,"sourceW":85,"sourceH":84},
"btn_bc_d229_cn_png":{"x":441,"y":91,"w":82,"h":84,"offX":2,"offY":0,"sourceW":85,"sourceH":84},
"btn_bc_d230_cn_png":{"x":441,"y":355,"w":81,"h":84,"offX":3,"offY":0,"sourceW":85,"sourceH":84},
"btn_bc_d232_cn_png":{"x":526,"y":267,"w":81,"h":84,"offX":2,"offY":0,"sourceW":85,"sourceH":84},
"btn_bc_d233_cn_png":{"x":268,"y":267,"w":83,"h":84,"offX":1,"offY":0,"sourceW":85,"sourceH":84},
"btn_bc_d234_cn_png":{"x":611,"y":355,"w":81,"h":83,"offX":3,"offY":1,"sourceW":85,"sourceH":84},
"btn_bc_d235_cn_png":{"x":442,"y":3,"w":82,"h":84,"offX":2,"offY":0,"sourceW":85,"sourceH":84},
"btn_bc_d239_cn_png":{"x":441,"y":179,"w":82,"h":84,"offX":2,"offY":0,"sourceW":85,"sourceH":84},
"btn_bc_d257_cn_png":{"x":612,"y":91,"w":81,"h":83,"offX":3,"offY":1,"sourceW":85,"sourceH":84},
"btn_bc_d258_cn_png":{"x":613,"y":3,"w":81,"h":83,"offX":3,"offY":1,"sourceW":85,"sourceH":84},
"btn_bc_d268_cn_png":{"x":354,"y":355,"w":83,"h":84,"offX":1,"offY":0,"sourceW":85,"sourceH":84},
"btn_bc_d270_cn_png":{"x":527,"y":91,"w":81,"h":84,"offX":3,"offY":0,"sourceW":85,"sourceH":84},
"btn_bc_d272_cn_png":{"x":355,"y":3,"w":83,"h":84,"offX":0,"offY":0,"sourceW":85,"sourceH":84},
"btn_bc_d284_cn_png":{"x":612,"y":178,"w":81,"h":83,"offX":3,"offY":1,"sourceW":85,"sourceH":84},
"btn_bc_d295_cn_png":{"x":528,"y":3,"w":81,"h":84,"offX":3,"offY":0,"sourceW":85,"sourceH":84},
"btn_bc_d300_cn_png":{"x":527,"y":179,"w":81,"h":84,"offX":3,"offY":0,"sourceW":85,"sourceH":84},
"btn_bc_d301_cn_png":{"x":3,"y":91,"w":85,"h":84},
"btn_bc_d304_cn_png":{"x":3,"y":179,"w":85,"h":84},
"btn_bc_d309_cn_png":{"x":3,"y":267,"w":85,"h":84},
"btn_bc_d310_cn_png":{"x":611,"y":267,"w":81,"h":84,"offX":3,"offY":0,"sourceW":85,"sourceH":84},
"btn_bc_d312_cn_png":{"x":3,"y":355,"w":85,"h":84},
"btn_bc_d314_cn_png":{"x":92,"y":3,"w":85,"h":84},
"btn_bc_d350_cn_png":{"x":92,"y":91,"w":85,"h":84},
"btn_bc_fr_d8_cn_png":{"x":783,"y":249,"w":74,"h":70},
"btn_bc_fr_d9_cn_png":{"x":697,"y":261,"w":74,"h":70},
"btn_bc_fr_d11_cn_png":{"x":783,"y":175,"w":74,"h":70},
"btn_bc_mi_12_cn_png":{"x":75,"y":443,"w":65,"h":53,"offX":5,"offY":0,"sourceW":70,"sourceH":53},
"btn_bc_mi_26_cn_png":{"x":144,"y":443,"w":65,"h":53,"offX":3,"offY":0,"sourceW":70,"sourceH":53},
"btn_bc_mi_27_cn_png":{"x":3,"y":443,"w":68,"h":53,"offX":1,"offY":0,"sourceW":70,"sourceH":53},
"btn_bc_tt_3_png":{"x":213,"y":443,"w":45,"h":45},
"btn_bc_tt_4_png":{"x":262,"y":443,"w":45,"h":45},
"btn_bc_tt_5_png":{"x":311,"y":443,"w":45,"h":45}}}