{
"file":"cece0.png",
"frames":{
"btn_cece_a1_cn_png":{"x":794,"y":222,"w":84,"h":83,"offX":11,"offY":11,"sourceW":106,"sourceH":94},
"btn_cece_a2_cn_png":{"x":794,"y":309,"w":84,"h":83,"offX":11,"offY":11,"sourceW":106,"sourceH":94},
"btn_cece_a3_cn_png":{"x":665,"y":222,"w":84,"h":83,"offX":11,"offY":11,"sourceW":106,"sourceH":94},
"btn_cece_a4_cn_png":{"x":778,"y":407,"w":75,"h":66,"offX":1,"offY":3,"sourceW":78,"sourceH":70},
"btn_cece_a5_cn_png":{"x":644,"y":337,"w":146,"h":66,"offX":0,"offY":15,"sourceW":152,"sourceH":96},
"btn_cece_a6_cn_png":{"x":628,"y":407,"w":146,"h":66,"offX":0,"offY":15,"sourceW":152,"sourceH":96},
"btn_cece_a7_cn_png":{"x":517,"y":199,"w":124,"h":43,"offX":10,"offY":14,"sourceW":142,"sourceH":70},
"btn_cece_a8_png":{"x":3,"y":403,"w":268,"h":81,"offX":0,"offY":6,"sourceW":268,"sourceH":92},
"btn_cece_a9_png":{"x":665,"y":174,"w":138,"h":44,"offX":8,"offY":0,"sourceW":154,"sourceH":44},
"btn_cece_a10_png":{"x":518,"y":364,"w":106,"h":106},
"btn_cece_a11_png":{"x":857,"y":396,"w":48,"h":47,"offX":4,"offY":5,"sourceW":56,"sourceH":56},
"cece_b1_cn_png":{"x":3,"y":199,"w":510,"h":84,"offX":2,"offY":0,"sourceW":512,"sourceH":85},
"cece_b2_png":{"x":3,"y":364,"w":511,"h":35,"offX":65,"offY":0,"sourceW":640,"sourceH":35},
"cece_b3_cn_png":{"x":3,"y":287,"w":637,"h":73,"offX":3,"offY":11,"sourceW":640,"sourceH":94},
"cece_b4_cn_png":{"x":3,"y":3,"w":640,"h":192,"offX":0,"offY":1,"sourceW":640,"sourceH":195},
"cece_b5_cn_png":{"x":517,"y":246,"w":62,"h":34},
"cece_b6_png":{"x":647,"y":3,"w":14,"h":330,"offX":22,"offY":0,"sourceW":58,"sourceH":330},
"cece_b8_png":{"x":665,"y":3,"w":172,"h":167,"offX":0,"offY":4,"sourceW":174,"sourceH":174},
"cece_b9_cn_png":{"x":275,"y":440,"w":133,"h":40},
"cece_b10_png":{"x":275,"y":403,"w":143,"h":33}}}