{"width":512,"imagePath":"mbody_2_tex.png","height":1024,"name":"mbody_2","SubTexture":[{"width":1,"y":872,"height":1,"name":"kong","x":230},{"width":93,"y":545,"height":309,"name":"艾兰迪素体/左手","x":268},{"width":227,"y":1,"height":542,"name":"艾兰迪素体/下身","x":1},{"width":164,"y":545,"height":360,"name":"艾兰迪素体/上身","x":1},{"width":99,"y":545,"height":325,"name":"艾兰迪素体/右手","x":167},{"width":87,"y":856,"height":119,"name":"艾兰迪素体/头部","x":268},{"width":61,"y":872,"height":32,"name":"艾兰迪素体/闭眼","x":167},{"width":39,"y":907,"height":32,"name":"艾兰迪素体/右眼闭","x":1},{"width":61,"y":906,"height":30,"name":"艾兰迪素体/左眼闭","x":167}]}