{"width":1643,"imagePath":"tx_30013_tex.png","height":753,"name":"tx_30013","SubTexture":[{"frameY":-2,"y":648,"frameWidth":26,"frameX":-3,"frameHeight":32,"width":19,"height":26,"name":"hb","x":1},{"frameY":-2,"y":702,"frameWidth":20,"frameX":0,"frameHeight":31,"width":17,"height":26,"name":"hb1","x":1},{"frameY":-6,"y":676,"frameWidth":28,"frameX":-6,"frameHeight":32,"width":19,"height":24,"name":"hb2","x":1},{"frameY":-11,"y":730,"frameWidth":31,"frameX":-4,"frameHeight":41,"width":21,"height":21,"name":"hb3","x":1},{"width":668,"y":1,"height":569,"name":"shu","x":1},{"width":426,"y":1,"height":744,"name":"shu1","x":671},{"width":542,"y":1,"height":477,"name":"shu2","x":1099},{"width":74,"y":572,"height":74,"name":"Star","x":1}]}