{
"file":"baixiaosi1.png",
"frames":{
"btn_bxs_b5_png":{"x":743,"y":3,"w":236,"h":85},
"btn_bxs_b13_cn_png":{"x":712,"y":851,"w":75,"h":61},
"btn_bxs_h2_png":{"x":714,"y":755,"w":153,"h":44},
"btn_bxs_h3_png":{"x":714,"y":803,"w":153,"h":44},
"bxs_a1_cn_png":{"x":381,"y":3,"w":358,"h":94,"offX":18,"offY":5,"sourceW":394,"sourceH":104},
"bxs_a5_cn_png":{"x":563,"y":524,"w":137,"h":26},
"bxs_a12_png":{"x":3,"y":532,"w":271,"h":171},
"bxs_a15_png":{"x":278,"y":565,"w":305,"h":52},
"bxs_b1_cn_png":{"x":3,"y":424,"w":357,"h":104,"offX":18,"offY":0,"sourceW":394,"sourceH":104},
"bxs_b3_png":{"x":736,"y":458,"w":206,"h":109},
"bxs_b5_png":{"x":563,"y":358,"w":169,"h":162},
"bxs_b6_png":{"x":704,"y":177,"w":160,"h":159,"offX":1,"offY":0,"sourceW":169,"sourceH":162},
"bxs_b7_png":{"x":362,"y":706,"w":157,"h":160,"offX":9,"offY":0,"sourceW":169,"sourceH":162},
"bxs_b9_png":{"x":362,"y":870,"w":179,"h":139},
"bxs_b10_png":{"x":545,"y":824,"w":163,"h":97,"offX":8,"offY":0,"sourceW":179,"sourceH":97},
"bxs_b11_png":{"x":714,"y":654,"w":163,"h":97,"offX":8,"offY":0,"sourceW":179,"sourceH":97},
"bxs_b17_cn_png":{"x":3,"y":100,"w":357,"h":104,"offX":18,"offY":0,"sourceW":394,"sourceH":104},
"bxs_b18_cn_png":{"x":3,"y":208,"w":357,"h":104,"offX":18,"offY":0,"sourceW":394,"sourceH":104},
"bxs_b19_cn_png":{"x":3,"y":316,"w":357,"h":104,"offX":18,"offY":0,"sourceW":394,"sourceH":104},
"bxs_d1_png":{"x":3,"y":962,"w":307,"h":47},
"bxs_d5_cn_png":{"x":735,"y":593,"w":188,"h":57,"offX":0,"offY":8,"sourceW":191,"sourceH":65},
"bxs_e2_cn_png":{"x":192,"y":707,"w":166,"h":248,"offX":0,"offY":13,"sourceW":166,"sourceH":261},
"bxs_e3_cn_png":{"x":534,"y":101,"w":166,"h":253,"offX":0,"offY":8,"sourceW":166,"sourceH":261},
"bxs_e4_cn_png":{"x":364,"y":101,"w":166,"h":261},
"bxs_f1_png":{"x":735,"y":571,"w":189,"h":18},
"bxs_g2_png":{"x":3,"y":3,"w":374,"h":93,"offX":10,"offY":5,"sourceW":394,"sourceH":104},
"bxs_g11_png":{"x":3,"y":707,"w":185,"h":251},
"bxs_h1_png":{"x":364,"y":366,"w":195,"h":195},
"bxs_h6_cn_png":{"x":736,"y":340,"w":190,"h":114},
"bxs_h7_cn_png":{"x":523,"y":706,"w":187,"h":114,"offX":1,"offY":0,"sourceW":190,"sourceH":114},
"bxs_j2_cn_png":{"x":278,"y":621,"w":228,"h":81},
"bxs_j3_cn_png":{"x":743,"y":92,"w":228,"h":81},
"bxs_panel3_png":{"x":881,"y":841,"w":86,"h":80},
"bxs_x2_png":{"x":677,"y":643,"w":30,"h":31,"offX":4,"offY":3,"sourceW":38,"sourceH":38},
"bxs_x3_png":{"x":607,"y":643,"w":31,"h":31,"offX":3,"offY":3,"sourceW":38,"sourceH":38},
"bxs_x4_png":{"x":704,"y":136,"w":31,"h":31,"offX":3,"offY":3,"sourceW":38,"sourceH":38},
"bxs_x5_png":{"x":903,"y":277,"w":31,"h":31,"offX":3,"offY":3,"sourceW":38,"sourceH":38},
"bxs_x6_png":{"x":642,"y":643,"w":31,"h":31,"offX":3,"offY":3,"sourceW":38,"sourceH":38},
"bxs_x7_png":{"x":314,"y":959,"w":31,"h":31,"offX":3,"offY":3,"sourceW":38,"sourceH":38},
"bxs_x8_png":{"x":735,"y":916,"w":31,"h":31,"offX":3,"offY":3,"sourceW":38,"sourceH":38},
"bxs_x9_png":{"x":735,"y":951,"w":31,"h":31,"offX":3,"offY":3,"sourceW":38,"sourceH":38},
"bxs_x12_png":{"x":704,"y":101,"w":31,"h":31,"offX":3,"offY":3,"sourceW":38,"sourceH":38},
"bxs_x14_png":{"x":868,"y":277,"w":31,"h":31,"offX":3,"offY":3,"sourceW":38,"sourceH":38},
"bxs_z1_png":{"x":791,"y":851,"w":86,"h":90,"offX":6,"offY":3,"sourceW":98,"sourceH":98},
"bxs_z2_png":{"x":868,"y":177,"w":85,"h":96,"offX":8,"offY":2,"sourceW":98,"sourceH":98},
"bxs_z3_png":{"x":510,"y":621,"w":93,"h":81,"offX":4,"offY":11,"sourceW":98,"sourceH":98},
"bxs_z4_png":{"x":643,"y":925,"w":88,"h":84,"offX":6,"offY":7,"sourceW":98,"sourceH":98},
"bxs_z5_png":{"x":871,"y":755,"w":79,"h":82,"offX":11,"offY":8,"sourceW":98,"sourceH":98},
"bxs_z8_png":{"x":607,"y":554,"w":89,"h":85,"offX":4,"offY":6,"sourceW":98,"sourceH":98},
"bxs_z9_png":{"x":545,"y":925,"w":94,"h":84,"offX":2,"offY":8,"sourceW":98,"sourceH":98},
"bxs_z11_png":{"x":881,"y":925,"w":92,"h":71,"offX":3,"offY":13,"sourceW":98,"sourceH":98},
"bxs_z12_png":{"x":881,"y":654,"w":84,"h":92,"offX":8,"offY":1,"sourceW":98,"sourceH":98}}}