{"file":"eff_sysd_01_tex.png","mc":{"eff_sysd_01":{"frames":[{"y":-93,"duration":1,"res":"Animation_0","x":-108},{"y":-93,"duration":1,"res":"Animation_1","x":-108},{"y":-93,"duration":1,"res":"Animation_2","x":-107},{"y":-95,"duration":1,"res":"Animation_3","x":-103},{"y":-96,"duration":1,"res":"Animation_4","x":-103},{"y":-93,"duration":1,"res":"Animation_5","x":-101},{"y":-93,"duration":1,"res":"Animation_6","x":-99},{"y":-93,"duration":1,"res":"Animation_7","x":-99},{"y":-93,"duration":1,"res":"Animation_8","x":-96},{"y":-93,"duration":1,"res":"Animation_9","x":-96},{"y":-93,"duration":1,"res":"Animation_10","x":-97},{"y":-93,"duration":1,"res":"Animation_11","x":-98},{"y":-93,"duration":1,"res":"Animation_12","x":-101},{"y":-93,"duration":1,"res":"Animation_13","x":-103},{"y":-91,"duration":1,"res":"Animation_14","x":-103},{"y":-89,"duration":1,"res":"Animation_15","x":-103},{"y":-90,"duration":1,"res":"Animation_16","x":-106},{"y":-93,"duration":1,"res":"Animation_17","x":-106},{"y":-93,"duration":1,"res":"Animation_18","x":-107},{"y":-94,"duration":1,"res":"Animation_19","x":-107},{"y":-94,"duration":1,"res":"Animation_20","x":-107},{"y":-94,"duration":1,"res":"Animation_21","x":-108},{"y":-94,"duration":1,"res":"Animation_22","x":-108}],"labels":[{"end":23,"frame":1,"name":"Animation"}],"frameRate":25,"events":[]}},"res":{"Animation_20":{"x":1,"y":1,"w":215,"h":192},"Animation_5":{"x":641,"y":385,"w":206,"h":186},"Animation_16":{"x":425,"y":385,"w":214,"h":180},"Animation_19":{"x":218,"y":1,"w":215,"h":192},"Animation_22":{"x":435,"y":1,"w":212,"h":192},"Animation_2":{"x":435,"y":195,"w":212,"h":188},"Animation_0":{"x":649,"y":1,"w":212,"h":191},"Animation_9":{"x":630,"y":573,"w":199,"h":176},"Animation_17":{"x":218,"y":195,"w":215,"h":186},"Animation_3":{"x":1,"y":573,"w":208,"h":188},"Animation_6":{"x":425,"y":567,"w":203,"h":186},"Animation_13":{"x":1,"y":763,"w":203,"h":173},"Animation_12":{"x":630,"y":751,"w":202,"h":173},"Animation_10":{"x":207,"y":944,"w":198,"h":168},"Animation_1":{"x":1,"y":383,"w":212,"h":188},"Animation_14":{"x":1,"y":938,"w":204,"h":172},"Animation_4":{"x":215,"y":383,"w":208,"h":189},"Animation_7":{"x":211,"y":574,"w":204,"h":183},"Animation_11":{"x":417,"y":929,"w":198,"h":171},"Animation_15":{"x":417,"y":755,"w":203,"h":172},"Animation_18":{"x":1,"y":195,"w":215,"h":186},"Animation_8":{"x":211,"y":759,"w":199,"h":183},"Animation_21":{"x":649,"y":194,"w":213,"h":189}}}