{"res":{"eff_yycx_03_12":{"x":0,"y":0,"w":146,"h":154},"eff_yycx_03_8":{"x":147,"y":0,"w":146,"h":154},"eff_yycx_03_4":{"x":294,"y":0,"w":146,"h":154},"eff_yycx_03_2":{"x":0,"y":155,"w":146,"h":154},"eff_yycx_03_0":{"x":147,"y":310,"w":92,"h":94},"eff_yycx_03_6":{"x":147,"y":155,"w":146,"h":154},"eff_yycx_03_10":{"x":294,"y":155,"w":146,"h":154},"eff_yycx_03_14":{"x":0,"y":310,"w":146,"h":154}},"file":"eff_yycx_03_tex.png","mc":{"eff_yycx_03":{"labels":[{"end":18,"frame":1,"name":"eff_yycx_03"}],"frameRate":24,"frames":[{"res":"eff_yycx_03_0","y":-42,"duration":2,"x":-42},{"res":"eff_yycx_03_2","y":-77,"duration":2,"x":-73},{"res":"eff_yycx_03_4","y":-77,"duration":2,"x":-73},{"res":"eff_yycx_03_6","y":-77,"duration":2,"x":-73},{"res":"eff_yycx_03_8","y":-77,"duration":2,"x":-73},{"res":"eff_yycx_03_10","y":-77,"duration":2,"x":-73},{"res":"eff_yycx_03_12","y":-77,"duration":2,"x":-73},{"res":"eff_yycx_03_14","y":-77,"duration":2,"x":-73},{"res":"","y":0,"duration":2,"x":0}],"events":[]}}}