{
"width": 1884,"height": 2023,"name": "20740","imagePath": "20740_1_tex.png","SubTexture":[{"x":1663,"y":849,"width":125,"height":268,"name":"拉丁舞DB/上身"},{"x":1368,"y":1780,"width":113,"height":158,"name":"拉丁舞DB/光效1"},{"x":1606,"y":1404,"width":237,"height":160,"name":"拉丁舞DB/光效2"},{"x":972,"y":246,"width":387,"height":349,"name":"拉丁舞DB/光效3"},{"x":1689,"y":3,"width":160,"height":247,"name":"拉丁舞DB/光点1"},{"x":1367,"y":844,"width":292,"height":216,"name":"拉丁舞DB/光点2"},{"x":839,"y":1526,"width":333,"height":223,"name":"拉丁舞DB/光点3"},{"x":1166,"y":1271,"width":270,"height":206,"name":"拉丁舞DB/光点4"},{"x":857,"y":881,"width":416,"height":215,"name":"拉丁舞DB/光点5"},{"x":491,"y":1813,"width":304,"height":206,"name":"拉丁舞DB/光点6"},{"x":799,"y":1753,"width":333,"height":197,"name":"拉丁舞DB/光点7"},{"x":839,"y":1271,"width":323,"height":251,"name":"拉丁舞DB/光点8"},{"x":977,"y":1954,"width":76,"height":66,"name":"拉丁舞DB/刘海"},{"x":1176,"y":1683,"width":280,"height":93,"name":"拉丁舞DB/右手"},{"x":491,"y":1271,"width":188,"height":538,"name":"拉丁舞DB/右腿"},{"x":3,"y":1271,"width":484,"height":742,"name":"拉丁舞DB/围栏前1"},{"x":1363,"y":246,"width":300,"height":318,"name":"拉丁舞DB/围栏前2"},{"x":1423,"y":1529,"width":167,"height":148,"name":"拉丁舞DB/图层_1021"},{"x":972,"y":3,"width":713,"height":239,"name":"拉丁舞DB/地饰光晕"},{"x":3,"y":670,"width":850,"height":597,"name":"拉丁舞DB/地饰底"},{"x":3,"y":3,"width":965,"height":663,"name":"拉丁舞DB/地饰点"},{"x":1277,"y":1064,"width":329,"height":184,"name":"拉丁舞DB/地饰闪1"},{"x":1676,"y":501,"width":97,"height":344,"name":"拉丁舞DB/地饰闪2"},{"x":857,"y":1100,"width":348,"height":167,"name":"拉丁舞DB/地饰闪3"},{"x":1777,"y":501,"width":94,"height":323,"name":"拉丁舞DB/地饰闪4"},{"x":1610,"y":1121,"width":241,"height":279,"name":"拉丁舞DB/地饰飘带1"},{"x":1792,"y":828,"width":89,"height":94,"name":"拉丁舞DB/头饰闪"},{"x":1485,"y":1681,"width":98,"height":288,"name":"拉丁舞DB/左手"},{"x":683,"y":1271,"width":152,"height":385,"name":"拉丁舞DB/左腿"},{"x":1594,"y":1568,"width":171,"height":132,"name":"拉丁舞DB/星星"},{"x":1209,"y":1100,"width":40,"height":141,"name":"拉丁舞DB/珠链1"},{"x":1792,"y":926,"width":74,"height":173,"name":"拉丁舞DB/珠链2"},{"x":799,"y":1954,"width":174,"height":66,"name":"拉丁舞DB/珠链3"},{"x":1440,"y":1429,"width":139,"height":96,"name":"拉丁舞DB/珠链4"},{"x":1186,"y":1967,"width":42,"height":46,"name":"拉丁舞DB/花0"},{"x":1730,"y":1879,"width":65,"height":85,"name":"拉丁舞DB/花1"},{"x":1057,"y":1954,"width":67,"height":47,"name":"拉丁舞DB/花2"},{"x":1610,"y":1064,"width":47,"height":49,"name":"拉丁舞DB/花3"},{"x":683,"y":1789,"width":23,"height":20,"name":"拉丁舞DB/花4"},{"x":683,"y":1704,"width":97,"height":81,"name":"拉丁舞DB/花5"},{"x":1759,"y":1798,"width":83,"height":77,"name":"拉丁舞DB/花6"},{"x":1759,"y":1726,"width":101,"height":68,"name":"拉丁舞DB/花7"},{"x":1777,"y":828,"width":11,"height":17,"name":"拉丁舞DB/花8"},{"x":1368,"y":1942,"width":40,"height":61,"name":"拉丁舞DB/花9"},{"x":1367,"y":568,"width":305,"height":272,"name":"拉丁舞DB/裙后"},{"x":972,"y":599,"width":391,"height":278,"name":"拉丁舞DB/裙子"},{"x":1799,"y":1879,"width":47,"height":95,"name":"拉丁舞DB/裙花1"},{"x":683,"y":1660,"width":150,"height":40,"name":"拉丁舞DB/裙花2"},{"x":1769,"y":1568,"width":112,"height":154,"name":"拉丁舞DB/闪星1"},{"x":1136,"y":1780,"width":228,"height":183,"name":"拉丁舞DB/闪星2"},{"x":1440,"y":1252,"width":162,"height":173,"name":"拉丁舞DB/闪星3"},{"x":1587,"y":1843,"width":139,"height":139,"name":"拉丁舞DB/闪星4"},{"x":1855,"y":1103,"width":26,"height":31,"name":"拉丁舞DB/闪星5"},{"x":1277,"y":881,"width":80,"height":174,"name":"拉丁舞DB/闪星6"},{"x":1587,"y":1704,"width":168,"height":135,"name":"拉丁舞DB/闪星8"},{"x":1128,"y":1967,"width":54,"height":41,"name":"拉丁舞DB/项链"},{"x":857,"y":670,"width":103,"height":197,"name":"拉丁舞DB/飘带后1"},{"x":1176,"y":1481,"width":243,"height":198,"name":"拉丁舞DB/飘带后2"},{"x":1667,"y":254,"width":194,"height":243,"name":"拉丁舞DB/飘带后3"}]}