{
"width": 1936,"height": 1500,"name": "24010","imagePath": "24010_2_tex.png","SubTexture":[{"x":143,"y":208,"width":262,"height":447,"name":"2401_bg_3"},{"x":936,"y":771,"width":997,"height":726,"name":"2401_bg_12"},{"x":3,"y":771,"width":929,"height":468,"name":"2401_bg_20"},{"x":3,"y":3,"width":784,"height":201,"name":"2401_bg_23"},{"x":409,"y":387,"width":1317,"height":380,"name":"2401_bg_24"},{"x":791,"y":3,"width":1118,"height":380,"name":"2401_bg_244"},{"x":3,"y":208,"width":136,"height":432,"name":"2401_ren_7"}]}