{
"width": 420,"height": 1505,"name": "25110","imagePath": "25110_0_tex.png","SubTexture":[{"x":3,"y":569,"width":350,"height":404,"name":"25110锦帷香舆换姿-DB/人物左袖"},{"x":33,"y":3,"width":104,"height":131,"name":"25110锦帷香舆换姿-DB/刘海"},{"x":3,"y":170,"width":339,"height":395,"name":"25110锦帷香舆换姿-DB/右"},{"x":3,"y":3,"width":11,"height":41,"name":"25110锦帷香舆换姿-DB/图层_47"},{"x":141,"y":3,"width":140,"height":163,"name":"25110锦帷香舆换姿-DB/头冠"},{"x":3,"y":977,"width":414,"height":525,"name":"25110锦帷香舆换姿-DB/绿裙"},{"x":18,"y":3,"width":11,"height":43,"name":"25110锦帷香舆换姿-DB/耳环"}]}