{
"file":"aacxxf0.png",
"frames":{
"aacxxf_c2_cn_png":{"x":611,"y":3,"w":397,"h":140,"offX":136,"offY":10,"sourceW":640,"sourceH":150},
"aacxxf_c7_cn_png":{"x":3,"y":755,"w":634,"h":223,"offX":0,"offY":7,"sourceW":640,"sourceH":240},
"aacxxf_c8_cn_png":{"x":3,"y":300,"w":634,"h":224,"offX":0,"offY":6,"sourceW":640,"sourceH":240},
"aacxxf_c10_cn_png":{"x":3,"y":528,"w":634,"h":223,"offX":0,"offY":7,"sourceW":640,"sourceH":240},
"aacxxf_c11_cn_png":{"x":449,"y":982,"w":133,"h":29,"offX":8,"offY":10,"sourceW":150,"sourceH":50},
"aacxxf_c17_cn_png":{"x":611,"y":147,"w":318,"h":111,"offX":139,"offY":33,"sourceW":640,"sourceH":150},
"aacxxf_c21_png":{"x":805,"y":783,"w":110,"h":39,"offX":0,"offY":4,"sourceW":110,"sourceH":45},
"aacxxf_c24_png":{"x":641,"y":659,"w":160,"h":159,"offX":0,"offY":1,"sourceW":160,"sourceH":160},
"aacxxf_c27_cn_png":{"x":886,"y":915,"w":104,"h":50,"offX":7,"offY":7,"sourceW":120,"sourceH":64},
"aacxxf_d1_png":{"x":891,"y":369,"w":96,"h":120,"offX":0,"offY":0,"sourceW":96,"sourceH":122},
"aacxxf_d2_png":{"x":805,"y":659,"w":96,"h":120,"offX":0,"offY":0,"sourceW":96,"sourceH":122},
"aacxxf_e1_png":{"x":777,"y":826,"w":84,"h":92,"offX":0,"offY":5,"sourceW":84,"sourceH":97},
"aacxxf_g3_png":{"x":641,"y":262,"w":37,"h":380,"offX":7,"offY":0,"sourceW":50,"sourceH":380},
"aacxxf_g4_png":{"x":682,"y":262,"w":23,"h":377,"offX":13,"offY":0,"sourceW":50,"sourceH":380},
"aacxxf_g7_png":{"x":3,"y":982,"w":442,"h":35,"offX":0,"offY":0,"sourceW":445,"sourceH":35},
"aacxxf_panel3_png":{"x":3,"y":3,"w":604,"h":293},
"aacxxf_panel4_png":{"x":709,"y":262,"w":87,"h":309,"offX":0,"offY":0,"sourceW":87,"sourceH":310},
"aacxxf_panel5_png":{"x":800,"y":262,"w":87,"h":309,"offX":0,"offY":0,"sourceW":87,"sourceH":310},
"btn_aacxxf_a1_cn_png":{"x":905,"y":669,"w":94,"h":110,"offX":14,"offY":5,"sourceW":125,"sourceH":120},
"btn_aacxxf_a7_png":{"x":891,"y":262,"w":124,"h":103,"offX":9,"offY":21,"sourceW":136,"sourceH":135},
"btn_aacxxf_a8_png":{"x":891,"y":262,"w":124,"h":103,"offX":9,"offY":21,"sourceW":136,"sourceH":135},
"btn_aacxxf_a17_png":{"x":709,"y":575,"w":211,"h":80,"offX":30,"offY":0,"sourceW":270,"sourceH":80},
"btn_aacxxf_a18_cn_png":{"x":641,"y":958,"w":152,"h":51,"offX":13,"offY":0,"sourceW":176,"sourceH":51},
"btn_aacxxf_a20_png":{"x":933,"y":147,"w":80,"h":111,"offX":7,"offY":5,"sourceW":90,"sourceH":120},
"btn_aacxxf_a21_png":{"x":924,"y":550,"w":84,"h":115,"offX":5,"offY":3,"sourceW":90,"sourceH":120},
"btn_aacxxf_b7_cn_png":{"x":865,"y":826,"w":86,"h":85,"offX":6,"offY":6,"sourceW":100,"sourceH":100},
"btn_aacxxf_b8_cn_png":{"x":797,"y":922,"w":85,"h":85,"offX":6,"offY":6,"sourceW":100,"sourceH":100},
"btn_aacxxf_f4_cn_png":{"x":891,"y":493,"w":108,"h":53,"offX":2,"offY":4,"sourceW":110,"sourceH":60},
"btn_aacxxf_f7_cn_png":{"x":641,"y":822,"w":132,"h":132,"offX":14,"offY":11,"sourceW":160,"sourceH":160},
"btn_aacxxf_f8_cn_png":{"x":641,"y":958,"w":152,"h":51,"offX":13,"offY":0,"sourceW":176,"sourceH":51}}}