{
"file":"glazeshop0.png",
"frames":{
"btn_cg_a6_png":{"x":436,"y":73,"w":50,"h":50},
"btn_cg_a9_cn_png":{"x":436,"y":3,"w":58,"h":66},
"btn_cg_a14_png":{"x":212,"y":260,"w":180,"h":77},
"btn_cg_a18_cn_png":{"x":396,"y":260,"w":88,"h":94},
"cg_a1_png":{"x":3,"y":483,"w":267,"h":6},
"cg_a2_png":{"x":436,"y":179,"w":21,"h":21},
"cg_a3_png":{"x":212,"y":403,"w":181,"h":39},
"cg_a4_png":{"x":3,"y":447,"w":213,"h":32},
"cg_a5_png":{"x":322,"y":457,"w":154,"h":36},
"cg_a7_png":{"x":436,"y":127,"w":51,"h":48},
"cg_a8_cn_png":{"x":392,"y":358,"w":71,"h":41},
"cg_a10_cn_png":{"x":220,"y":446,"w":98,"h":27},
"cg_a11_cn_png":{"x":397,"y":403,"w":101,"h":50},
"cg_a12_cn_png":{"x":227,"y":223,"w":198,"h":33},
"cg_a13_cn_png":{"x":212,"y":341,"w":176,"h":58},
"cg_a15_png":{"x":3,"y":3,"w":220,"h":220},
"cg_a16_png":{"x":3,"y":227,"w":205,"h":216},
"cg_a18_png":{"x":227,"y":3,"w":205,"h":216}}}